{
    "Adobe Acrobat": {
        "Windows": {
            "Ctrl + N": {
                "Description": "Create new PDF",
                "Category": "File Management"
            },
            "Ctrl + +": {
                "Description": "Zoom in",
                "Category": "View"
            },
            "Ctrl + -": {
                "Description": "Zoom out",
                "Category": "View"
            },
            "Ctrl + F": {
                "Description": "Find text",
                "Category": "Search"
            },
            "Ctrl + S": {
                "Description": "Save document",
                "Category": "File Management"
            }
        }
    },
    "Adobe After Effects": {
        "Windows": {
            "Ctrl + M": {
                "Description": "Add to render queue",
                "Category": "Rendering"
            },
            "0 (Numpad)": {
                "Description": "Preview composition",
                "Category": "Playback"
            },
            "U": {
                "Description": "Reveal properties",
                "Category": "Layer Management"
            },
            "U U": {
                "Description": "Show keyframes only",
                "Category": "Animation"
            },
            "Ctrl + D": {
                "Description": "Duplicate layer",
                "Category": "Editing"
            }
        }
    },
    "Adobe Illustrator": {
        "Windows": {
            "Ctrl + N": {
                "Description": "New document",
                "Category": "File Management"
            },
            "Ctrl + C": {
                "Description": "Copy",
                "Category": "Editing"
            },
            "Ctrl + +": {
                "Description": "Zoom in",
                "Category": "View"
            },
            "Ctrl + -": {
                "Description": "Zoom out",
                "Category": "View"
            },
            "Ctrl + V": {
                "Description": "Paste",
                "Category": "Editing"
            }
        }
    },
    "Adobe InDesign": {
        "Windows": {
            "Ctrl + Alt + L": {
                "Description": "Unlock all on spread",
                "Category": "Object Management"
            },
            "Ctrl + D": {
                "Description": "Place file",
                "Category": "File Management"
            },
            "Ctrl + N": {
                "Description": "New document",
                "Category": "File Management"
            },
            "Ctrl + Alt + Shift + E": {
                "Description": "Fit content proportionally",
                "Category": "Layout"
            },
            "Ctrl + L": {
                "Description": "Lock object",
                "Category": "Object Management"
            }
        }
    },
    "Adobe Lightroom": {
        "Windows": {
            "Ctrl + Shift + D": {
                "Description": "Deselect all photos",
                "Category": "Selection"
            },
            "P": {
                "Description": "Flag photo as pick",
                "Category": "Flagging"
            },
            "Ctrl + Alt + 1": {
                "Description": "Switch to Library module",
                "Category": "Navigation"
            },
            "Ctrl + Alt + 2": {
                "Description": "Switch to Develop module",
                "Category": "Navigation"
            },
            "R": {
                "Description": "Crop photo",
                "Category": "Editing"
            }
        }
    },
    "Adobe Photoshop": {
        "Windows": {
            "Shift + Ctrl + N": {
                "Description": "New layer",
                "Category": "Layers"
            },
            "Ctrl + A": {
                "Description": "Select all",
                "Category": "Selection"
            },
            "Ctrl + D": {
                "Description": "Deselect",
                "Category": "Selection"
            },
            "Ctrl + T": {
                "Description": "Free transform",
                "Category": "Editing"
            },
            "Ctrl + +": {
                "Description": "Zoom in",
                "Category": "View"
            }
        }
    },
    "Adobe Premiere Pro": {
        "Windows": {
            "O": {
                "Description": "Mark out",
                "Category": "Markers"
            },
            "Space": {
                "Description": "Play/Stop playback",
                "Category": "Playback"
            },
            "Ctrl + D": {
                "Description": "Add video transition",
                "Category": "Editing"
            },
            "I": {
                "Description": "Mark in",
                "Category": "Markers"
            },
            "Ctrl + K": {
                "Description": "Cut clip at playhead",
                "Category": "Editing"
            }
        }
    },
    "Affinity Designer": {
        "Windows": {
            "Ctrl + V": {
                "Description": "Paste",
                "Category": "Editing"
            },
            "Ctrl + N": {
                "Description": "New document",
                "Category": "File Management"
            },
            "Ctrl + C": {
                "Description": "Copy",
                "Category": "Editing"
            },
            "Ctrl + J": {
                "Description": "Duplicate object",
                "Category": "Editing"
            },
            "Ctrl + 0": {
                "Description": "Zoom to fit",
                "Category": "View"
            }
        }
    },
    "Affinity Photo": {
        "Windows": {
            "Ctrl + N": {
                "Description": "New document",
                "Category": "File Management"
            },
            "Ctrl + E": {
                "Description": "Merge layers",
                "Category": "Layers"
            },
            "Ctrl + Shift + I": {
                "Description": "Invert selection",
                "Category": "Selection"
            },
            "Ctrl + J": {
                "Description": "Duplicate layer",
                "Category": "Layers"
            },
            "Ctrl + O": {
                "Description": "Open document",
                "Category": "File Management"
            }
        }
    },
    "Airtable": {
        "Windows": {
            "Shift + Space": {
                "Description": "Expand selected record",
                "Category": "View"
            },
            "Ctrl + Shift + G": {
                "Description": "Toggle grid/list view",
                "Category": "View"
            },
            "Ctrl + D": {
                "Description": "Duplicate selected record",
                "Category": "Data Management"
            },
            "Ctrl + Alt + N": {
                "Description": "Add a new record",
                "Category": "Data Entry"
            },
            "Ctrl + F": {
                "Description": "Search records",
                "Category": "Search"
            }
        }
    },
    "Asana": {
        "Windows": {
            "Tab + H": {
                "Description": "Assign task to yourself",
                "Category": "Tasks"
            },
            "Tab + Q": {
                "Description": "Add new task",
                "Category": "Tasks"
            },
            "Tab + Enter": {
                "Description": "Toggle task details",
                "Category": "Navigation"
            },
            "Tab + D": {
                "Description": "Set due date",
                "Category": "Tasks"
            },
            "Tab + X": {
                "Description": "Mark task as complete",
                "Category": "Tasks"
            }
        }
    },
    "Atom": {
        "Windows": {
            "Ctrl + \\": {
                "Description": "Toggle tree view",
                "Category": "View"
            },
            "Ctrl + Shift + P": {
                "Description": "Open command palette",
                "Category": "Tools"
            },
            "Ctrl + /": {
                "Description": "Toggle comment",
                "Category": "Editing"
            },
            "Ctrl + G": {
                "Description": "Go to line",
                "Category": "Navigation"
            },
            "Ctrl + Shift + F": {
                "Description": "Find in project",
                "Category": "Search"
            }
        }
    },
    "Audacity": {
        "Windows": {
            "Space": {
                "Description": "Play or stop",
                "Category": "Playback"
            },
            "Ctrl + X": {
                "Description": "Cut",
                "Category": "Editing"
            },
            "Ctrl + C": {
                "Description": "Copy",
                "Category": "Editing"
            },
            "Ctrl + V": {
                "Description": "Paste",
                "Category": "Editing"
            },
            "R": {
                "Description": "Record",
                "Category": "Recording"
            }
        }
    },
    "AutoCAD": {
        "Windows": {
            "E": {
                "Description": "Erase objects",
                "Category": "Editing"
            },
            "Ctrl + S": {
                "Description": "Save drawing",
                "Category": "File Management"
            },
            "M": {
                "Description": "Move objects",
                "Category": "Editing"
            },
            "Z": {
                "Description": "Zoom",
                "Category": "View"
            },
            "C": {
                "Description": "Circle command",
                "Category": "Drawing"
            },
            "L": {
                "Description": "Line command",
                "Category": "Drawing"
            },
            "RO": {
                "Description": "Rotate objects",
                "Category": "Editing"
            }
        }
    },
    "Basecamp": {
        "Windows": {
            "Ctrl + Alt + F": {
                "Description": "Search Basecamp",
                "Category": "Search"
            },
            "Ctrl + Alt + N": {
                "Description": "Add a new to-do",
                "Category": "Tasks"
            },
            "Ctrl + Alt + C": {
                "Description": "Toggle calendar",
                "Category": "View"
            },
            "Ctrl + Alt + G": {
                "Description": "Go to notifications",
                "Category": "Navigation"
            },
            "Ctrl + Shift + R": {
                "Description": "Mark all notifications as read",
                "Category": "Notifications"
            }
        }
    },
    "Blender": {
        "Windows": {
            "Z": {
                "Description": "Toggle wireframe mode",
                "Category": "View"
            },
            "G": {
                "Description": "Grab/move object",
                "Category": "Transform"
            },
            "S": {
                "Description": "Scale object",
                "Category": "Transform"
            },
            "Shift + A": {
                "Description": "Add new mesh",
                "Category": "Inserting"
            },
            "R": {
                "Description": "Rotate object",
                "Category": "Transform"
            }
        }
    },
    "Canva": {
        "Windows": {
            "Ctrl + [": {
                "Description": "Send element backward",
                "Category": "Layer Management"
            },
            "Ctrl + G": {
                "Description": "Group elements",
                "Category": "Editing"
            },
            "Ctrl + Shift + G": {
                "Description": "Ungroup elements",
                "Category": "Editing"
            },
            "Ctrl + Enter": {
                "Description": "Add a new page",
                "Category": "Page Management"
            },
            "Ctrl + ]": {
                "Description": "Bring element forward",
                "Category": "Layer Management"
            }
        }
    },
    "Confluence": {
        "Windows": {
            "Ctrl + S": {
                "Description": "Save page",
                "Category": "File Management"
            },
            "C": {
                "Description": "Create new page",
                "Category": "File Management"
            },
            "Ctrl + K": {
                "Description": "Insert link",
                "Category": "Inserting"
            },
            "Ctrl + B": {
                "Description": "Bold text",
                "Category": "Formatting"
            }
        }
    },
    "DaVinci Resolve": {
        "Windows": {
            "Ctrl + B": {
                "Description": "Split clip",
                "Category": "Editing"
            },
            "Ctrl + T": {
                "Description": "Add transition",
                "Category": "Editing"
            },
            "Space": {
                "Description": "Play/Stop playback",
                "Category": "Playback"
            },
            "Ctrl + Alt + V": {
                "Description": "Toggle timeline view options",
                "Category": "View"
            },
            "M": {
                "Description": "Add marker",
                "Category": "Markers"
            }
        }
    },
    "Discord": {
        "Windows": {
            "Ctrl + Shift + D": {
                "Description": "Toggle deafen",
                "Category": "Audio"
            },
            "Escape": {
                "Description": "Mark channel read",
                "Category": "Message Management"
            },
            "Ctrl + /": {
                "Description": "Show keyboard shortcuts",
                "Category": "Help"
            },
            "Alt + Arrow Keys": {
                "Description": "Navigate channels",
                "Category": "Navigation"
            },
            "Ctrl + Shift + M": {
                "Description": "Toggle mute",
                "Category": "Audio"
            }
        }
    },
    "Docker Desktop": {
        "Windows": {
            "Ctrl + S": {
                "Description": "Open settings",
                "Category": "Settings"
            },
            "Ctrl + Alt + C": {
                "Description": "Open command line",
                "Category": "Tools"
            },
            "Ctrl + D": {
                "Description": "Open dashboard",
                "Category": "Navigation"
            },
            "Ctrl + Shift + X": {
                "Description": "Stop container",
                "Category": "Container Management"
            },
            "Ctrl + Shift + S": {
                "Description": "Start container",
                "Category": "Container Management"
            }
        }
    },
    "Dropbox": {
        "Windows": {
            "Ctrl + Shift + S": {
                "Description": "Share selected file",
                "Category": "File Management"
            },
            "Ctrl + Alt + D": {
                "Description": "Open Dropbox folder",
                "Category": "Navigation"
            },
            "Ctrl + Shift + V": {
                "Description": "View file versions",
                "Category": "File Management"
            },
            "Ctrl + Alt + P": {
                "Description": "Pause syncing",
                "Category": "Sync"
            },
            "Ctrl + Shift + W": {
                "Description": "Open Dropbox website",
                "Category": "Navigation"
            }
        }
    },
    "Evernote": {
        "Windows": {
            "Ctrl + Shift + B": {
                "Description": "Insert bullet list",
                "Category": "Formatting"
            },
            "Ctrl + Alt + T": {
                "Description": "Add tag",
                "Category": "Tagging"
            },
            "Ctrl + F": {
                "Description": "Search notes",
                "Category": "Search"
            },
            "Ctrl + B": {
                "Description": "Bold text",
                "Category": "Formatting"
            },
            "F9": {
                "Description": "Sync notes",
                "Category": "Sync"
            },
            "Ctrl + N": {
                "Description": "New note",
                "Category": "File Management"
            }
        }
    },
    "Figma": {
        "Windows": {
            "Ctrl + Shift + O": {
                "Description": "Outline text",
                "Category": "Editing"
            },
            "Ctrl + G": {
                "Description": "Group selection",
                "Category": "Organization"
            },
            "Ctrl + Shift + G": {
                "Description": "Ungroup selection",
                "Category": "Organization"
            },
            "Ctrl + -": {
                "Description": "Zoom out",
                "Category": "View"
            },
            "Ctrl + +": {
                "Description": "Zoom in",
                "Category": "View"
            },
            "F11": {
                "Description": "Toggle fullscreen",
                "Category": "View"
            },
            "Ctrl + Shift + 4": {
                "Description": "Toggle layout grids",
                "Category": "View"
            },
            "Ctrl + /": {
                "Description": "Open search",
                "Category": "Search"
            }
        }
    },
    "Final Cut Pro": {
        "MacOS": {
            "W": {
                "Description": "Insert clip",
                "Category": "Editing"
            },
            "Space": {
                "Description": "Play/Pause",
                "Category": "Playback"
            },
            "S": {
                "Description": "Toggle skimming",
                "Category": "Editing"
            },
            "Cmd + B": {
                "Description": "Blade tool",
                "Category": "Editing"
            },
            "Shift + Z": {
                "Description": "Zoom to fit",
                "Category": "View"
            }
        }
    },
    "GIMP": {
        "Windows": {
            "Ctrl + O": {
                "Description": "Open image",
                "Category": "File Management"
            },
            "Ctrl + N": {
                "Description": "New image",
                "Category": "File Management"
            },
            "Ctrl + V": {
                "Description": "Paste selection",
                "Category": "Editing"
            },
            "Ctrl + C": {
                "Description": "Copy selection",
                "Category": "Editing"
            },
            "Ctrl + Z": {
                "Description": "Undo",
                "Category": "Editing"
            }
        }
    },
    "GitHub": {
        "Windows": {
            "Ctrl + F": {
                "Description": "Search in repository",
                "Category": "Search"
            },
            "Ctrl + Shift + P": {
                "Description": "Go to pull requests",
                "Category": "Navigation"
            },
            "Alt + N": {
                "Description": "Create new repository",
                "Category": "Repository Management"
            },
            "Ctrl + B": {
                "Description": "Toggle file explorer",
                "Category": "Navigation"
            },
            "Ctrl + Shift + I": {
                "Description": "View issues",
                "Category": "Issues"
            }
        }
    },
    "GitHub Desktop": {
        "Windows": {
            "Ctrl + Shift + F": {
                "Description": "Fetch origin",
                "Category": "Repository Management"
            },
            "Ctrl + 1": {
                "Description": "Show changes",
                "Category": "View"
            },
            "Ctrl + O": {
                "Description": "Open repository",
                "Category": "File Management"
            },
            "Ctrl + P": {
                "Description": "Push changes",
                "Category": "Repository Management"
            },
            "Ctrl + 2": {
                "Description": "Switch to history view",
                "Category": "View"
            }
        }
    },
    "Google Calendar": {
        "Windows": {
            "W": {
                "Description": "Switch to week view",
                "Category": "View"
            },
            "T": {
                "Description": "Go to today",
                "Category": "Navigation"
            },
            "C": {
                "Description": "Create new event",
                "Category": "Event Management"
            },
            "D": {
                "Description": "Switch to day view",
                "Category": "View"
            }
        }
    },
    "Google Chrome": {
        "Windows": {
            "Ctrl + Shift + O": {
                "Description": "Open bookmarks manager",
                "Category": "Bookmarks"
            },
            "Ctrl + T": {
                "Description": "Open new tab",
                "Category": "Navigation"
            },
            "Ctrl + Shift + N": {
                "Description": "Open incognito window",
                "Category": "Privacy"
            },
            "Ctrl + Shift + T": {
                "Description": "Reopen last closed tab",
                "Category": "Navigation"
            },
            "Ctrl + W": {
                "Description": "Close current tab",
                "Category": "Navigation"
            }
        }
    },
    "Google Docs": {
        "MacOS": {
            "Cmd + B": {
                "Description": "Bold text",
                "Category": "Formatting"
            },
            "Cmd + U": {
                "Description": "Underline text",
                "Category": "Formatting"
            },
            "Cmd + K": {
                "Description": "Insert link",
                "Category": "Inserting"
            },
            "Cmd + I": {
                "Description": "Italicize text",
                "Category": "Formatting"
            },
            "Cmd + Shift + H": {
                "Description": "Open find and replace",
                "Category": "Editing"
            }
        },
        "Windows": {
            "Ctrl + B": {
                "Description": "Bold text",
                "Category": "Formatting"
            },
            "Ctrl + K": {
                "Description": "Insert link",
                "Category": "Inserting"
            },
            "Ctrl + U": {
                "Description": "Underline text",
                "Category": "Formatting"
            },
            "Ctrl + I": {
                "Description": "Italicize text",
                "Category": "Formatting"
            },
            "Ctrl + H": {
                "Description": "Open find and replace",
                "Category": "Editing"
            }
        }
    },
    "Google Keep": {
        "Windows": {
            "Ctrl + Alt + N": {
                "Description": "Add new note",
                "Category": "Notes"
            },
            "Ctrl + Alt + P": {
                "Description": "Pin note",
                "Category": "Notes"
            },
            "Ctrl + F": {
                "Description": "Search notes",
                "Category": "Search"
            },
            "Ctrl + G": {
                "Description": "Toggle list view/grid view",
                "Category": "View"
            },
            "Ctrl + Alt + A": {
                "Description": "Archive note",
                "Category": "Notes"
            }
        }
    },
    "Google Meet": {
        "Windows": {
            "Ctrl + Alt + C": {
                "Description": "Open chat",
                "Category": "Communication"
            },
            "Ctrl + Shift + P": {
                "Description": "Pin/unpin screen",
                "Category": "View"
            },
            "Ctrl + E": {
                "Description": "Turn camera on/off",
                "Category": "Video"
            },
            "Ctrl + D": {
                "Description": "Mute/unmute microphone",
                "Category": "Audio"
            },
            "Ctrl + Alt + P": {
                "Description": "Show/hide people",
                "Category": "View"
            }
        }
    },
    "Google Sheets": {
        "Windows": {
            "Alt + Shift + F": {
                "Description": "Insert function",
                "Category": "Formula"
            },
            "Ctrl + B": {
                "Description": "Bold text",
                "Category": "Formatting"
            },
            "Ctrl + H": {
                "Description": "Open find and replace",
                "Category": "Editing"
            },
            "Ctrl + Shift + L": {
                "Description": "Toggle filter",
                "Category": "Data"
            },
            "Shift + F11": {
                "Description": "Insert new sheet",
                "Category": "Sheet Management"
            }
        }
    },
    "Google Slides": {
        "Windows": {
            "Ctrl + Shift + F5": {
                "Description": "Present from beginning",
                "Category": "Presentation"
            },
            "Ctrl + M": {
                "Description": "New slide",
                "Category": "Slides"
            },
            "Ctrl + Shift + E": {
                "Description": "Align center",
                "Category": "Formatting"
            },
            "Ctrl + D": {
                "Description": "Duplicate slide",
                "Category": "Slides"
            },
            "Ctrl + B": {
                "Description": "Bold text",
                "Category": "Formatting"
            }
        }
    },
    "Grammarly": {
        "Windows": {
            "F7": {
                "Description": "Check spelling and grammar",
                "Category": "Editing"
            },
            "Esc": {
                "Description": "Dismiss suggestion",
                "Category": "Editing"
            },
            "Enter": {
                "Description": "Accept suggestion",
                "Category": "Editing"
            },
            "Ctrl + Shift + S": {
                "Description": "Open settings",
                "Category": "Settings"
            },
            "Ctrl + G": {
                "Description": "Open Grammarly editor",
                "Category": "Tools"
            }
        }
    },
    "HubSpot": {
        "Windows": {
            "Ctrl + Alt + C": {
                "Description": "Create new contact",
                "Category": "Contacts"
            },
            "Ctrl + F": {
                "Description": "Search",
                "Category": "Search"
            },
            "Ctrl + Alt + T": {
                "Description": "Open tasks",
                "Category": "Tasks"
            },
            "Ctrl + Alt + D": {
                "Description": "Go to dashboard",
                "Category": "Navigation"
            },
            "Ctrl + Alt + G": {
                "Description": "View deals",
                "Category": "Deals"
            }
        }
    },
    "Inkscape": {
        "Windows": {
            "Shift + Ctrl + F": {
                "Description": "Toggle fill and stroke dialog",
                "Category": "Formatting"
            },
            "Ctrl + G": {
                "Description": "Group selected objects",
                "Category": "Editing"
            },
            "Ctrl + Shift + G": {
                "Description": "Ungroup selected objects",
                "Category": "Editing"
            },
            "Ctrl + D": {
                "Description": "Duplicate selected object",
                "Category": "Editing"
            },
            "Ctrl + Shift + A": {
                "Description": "Align selected objects",
                "Category": "Alignment"
            }
        }
    },
    "IntelliJ IDEA": {
        "Windows": {
            "Ctrl + E": {
                "Description": "Open recent files",
                "Category": "Navigation"
            },
            "Shift + F10": {
                "Description": "Run program",
                "Category": "Run"
            },
            "Ctrl + /": {
                "Description": "Comment/uncomment line",
                "Category": "Editing"
            },
            "Ctrl + N": {
                "Description": "Navigate to class",
                "Category": "Navigation"
            },
            "Alt + F7": {
                "Description": "Find usages",
                "Category": "Search"
            }
        }
    },
    "Jupyter Notebook": {
        "Windows": {
            "Shift + Enter": {
                "Description": "Run cell",
                "Category": "Execution"
            },
            "Ctrl + S": {
                "Description": "Save notebook",
                "Category": "File Management"
            },
            "Esc": {
                "Description": "Switch to command mode",
                "Category": "Navigation"
            },
            "D D": {
                "Description": "Delete cell",
                "Category": "Editing"
            },
            "B": {
                "Description": "Insert new cell below",
                "Category": "Editing"
            }
        }
    },
    "LibreOffice Calc": {
        "Windows": {
            "Ctrl + S": {
                "Description": "Save spreadsheet",
                "Category": "File Management"
            },
            "F11": {
                "Description": "Insert chart",
                "Category": "Inserting"
            },
            "Ctrl + Shift + B": {
                "Description": "Add border",
                "Category": "Formatting"
            },
            "Ctrl + N": {
                "Description": "New spreadsheet",
                "Category": "File Management"
            },
            "Ctrl + B": {
                "Description": "Bold text",
                "Category": "Formatting"
            }
        }
    },
    "LibreOffice Writer": {
        "Windows": {
            "Ctrl + S": {
                "Description": "Save document",
                "Category": "File Management"
            },
            "Ctrl + U": {
                "Description": "Underline text",
                "Category": "Formatting"
            },
            "Ctrl + P": {
                "Description": "Print document",
                "Category": "File Management"
            },
            "Ctrl + F": {
                "Description": "Open find dialog",
                "Category": "Editing"
            },
            "Ctrl + B": {
                "Description": "Bold text",
                "Category": "Formatting"
            }
        }
    },
    "Mailchimp": {
        "Windows": {
            "Ctrl + Alt + A": {
                "Description": "Open audience settings",
                "Category": "Audience Management"
            },
            "Ctrl + N": {
                "Description": "Create new campaign",
                "Category": "Campaign Management"
            },
            "Ctrl + R": {
                "Description": "Open reports",
                "Category": "Reports"
            },
            "Ctrl + P": {
                "Description": "Preview campaign",
                "Category": "Preview"
            },
            "Ctrl + Shift + S": {
                "Description": "Schedule campaign",
                "Category": "Campaign Management"
            }
        }
    },
    "Microsoft Access": {
        "Windows": {
            "Ctrl + O": {
                "Description": "Open database",
                "Category": "File Management"
            },
            "Ctrl + S": {
                "Description": "Save database",
                "Category": "File Management"
            },
            "Shift + F7": {
                "Description": "Filter by selection",
                "Category": "Data Management"
            },
            "Ctrl + +": {
                "Description": "Insert new record",
                "Category": "Data Management"
            },
            "Ctrl + -": {
                "Description": "Delete record",
                "Category": "Data Management"
            }
        }
    },
    "Microsoft Edge": {
        "Windows": {
            "Ctrl + J": {
                "Description": "Open downloads",
                "Category": "Navigation"
            },
            "Ctrl + T": {
                "Description": "Open new tab",
                "Category": "Navigation"
            },
            "Ctrl + H": {
                "Description": "Open history",
                "Category": "Navigation"
            },
            "Ctrl + Shift + T": {
                "Description": "Reopen closed tab",
                "Category": "Navigation"
            },
            "Ctrl + W": {
                "Description": "Close current tab",
                "Category": "Navigation"
            }
        }
    },
    "Microsoft Excel": {
        "Windows": {
            "Shift + F11": {
                "Description": "Insert a new worksheet",
                "Category": "Sheet Management"
            },
            "Alt + =": {
                "Description": "AutoSum",
                "Category": "Formula"
            },
            "Ctrl + 1": {
                "Description": "Open format cells dialog",
                "Category": "Formatting"
            },
            "Shift + Space": {
                "Description": "Select entire row",
                "Category": "Selection"
            },
            "Ctrl + Shift + L": {
                "Description": "Toggle filter",
                "Category": "Data"
            }
        }
    },
    "Microsoft OneNote": {
        "Windows": {
            "Ctrl + G": {
                "Description": "Open notebook pane",
                "Category": "Navigation"
            },
            "Ctrl + 1": {
                "Description": "Tag as important",
                "Category": "Tagging"
            },
            "Ctrl + E": {
                "Description": "Search notebooks",
                "Category": "Search"
            },
            "Ctrl + Shift + H": {
                "Description": "Highlight text",
                "Category": "Formatting"
            },
            "Ctrl + N": {
                "Description": "Create new page",
                "Category": "File Management"
            }
        }
    },
    "Microsoft Outlook": {
        "Windows": {
            "Ctrl + R": {
                "Description": "Reply to email",
                "Category": "Email Management"
            },
            "Ctrl + 2": {
                "Description": "Open calendar",
                "Category": "Navigation"
            },
            "Ctrl + U": {
                "Description": "Mark as read/unread",
                "Category": "Message Management"
            },
            "Ctrl + F": {
                "Description": "Forward email",
                "Category": "Email Management"
            },
            "Ctrl + Shift + M": {
                "Description": "New email",
                "Category": "Email Management"
            }
        }
    },
    "Microsoft Power BI": {
        "Windows": {
            "F5": {
                "Description": "Refresh data",
                "Category": "Data"
            },
            "Ctrl + Shift + F": {
                "Description": "Open fields pane",
                "Category": "Navigation"
            },
            "Ctrl + S": {
                "Description": "Save report",
                "Category": "File Management"
            },
            "Alt + N": {
                "Description": "Add new visual",
                "Category": "Visualization"
            },
            "Ctrl + Shift + L": {
                "Description": "Toggle filter pane",
                "Category": "Filters"
            }
        }
    },
    "Microsoft PowerPoint": {
        "Windows": {
            "Ctrl + D": {
                "Description": "Duplicate slide",
                "Category": "Slides"
            },
            "F5": {
                "Description": "Start presentation",
                "Category": "Presentation"
            },
            "Ctrl + B": {
                "Description": "Bold text",
                "Category": "Formatting"
            },
            "Ctrl + S": {
                "Description": "Save presentation",
                "Category": "File Management"
            },
            "Ctrl + M": {
                "Description": "New slide",
                "Category": "Slides"
            }
        }
    },
    "Microsoft Project": {
        "Windows": {
            "Alt + Right Arrow": {
                "Description": "Move to next day",
                "Category": "Navigation"
            },
            "Ctrl + Shift + N": {
                "Description": "New task",
                "Category": "Tasks"
            },
            "Ctrl + Shift + F2": {
                "Description": "Split task",
                "Category": "Tasks"
            },
            "Ctrl + Shift + F5": {
                "Description": "Zoom in on timeline",
                "Category": "View"
            },
            "Ctrl + F2": {
                "Description": "Link tasks",
                "Category": "Tasks"
            }
        }
    },
    "Microsoft Teams": {
        "Windows": {
            "Ctrl + E": {
                "Description": "Go to search",
                "Category": "Search"
            },
            "Ctrl + Shift + H": {
                "Description": "End call",
                "Category": "Call Management"
            },
            "Ctrl + Shift + M": {
                "Description": "Toggle mute",
                "Category": "Audio"
            },
            "Ctrl + Shift + U": {
                "Description": "Start video call",
                "Category": "Video"
            },
            "Ctrl + N": {
                "Description": "Start new chat",
                "Category": "Communication"
            }
        }
    },
    "Microsoft Word": {
        "Windows": {
            "Ctrl + E": {
                "Description": "Align text to center",
                "Category": "Formatting"
            },
            "Ctrl + O": {
                "Description": "Open document",
                "Category": "File Management"
            },
            "Ctrl + S": {
                "Description": "Save document",
                "Category": "File Management"
            },
            "Ctrl + F": {
                "Description": "Find text",
                "Category": "Editing"
            },
            "Ctrl + B": {
                "Description": "Bold text",
                "Category": "Formatting"
            }
        }
    },
    "Miro": {
        "Windows": {
            "Ctrl + Y": {
                "Description": "Redo last action",
                "Category": "Editing"
            },
            "T": {
                "Description": "Add a text box",
                "Category": "Inserting"
            },
            "Ctrl + Z": {
                "Description": "Undo last action",
                "Category": "Editing"
            },
            "N": {
                "Description": "Add a sticky note",
                "Category": "Inserting"
            },
            "Ctrl + +": {
                "Description": "Zoom in",
                "Category": "View"
            }
        }
    },
    "Monday.com": {
        "Windows": {
            "Ctrl + Shift + Right Arrow": {
                "Description": "Navigate to next board",
                "Category": "Navigation"
            },
            "Ctrl + F": {
                "Description": "Search in board",
                "Category": "Search"
            },
            "Ctrl + Shift + C": {
                "Description": "Mark item as complete",
                "Category": "Tasks"
            },
            "Ctrl + Alt + I": {
                "Description": "Add new item",
                "Category": "Tasks"
            },
            "Ctrl + Shift + N": {
                "Description": "Open notifications panel",
                "Category": "Notifications"
            }
        }
    },
    "Mozilla Thunderbird": {
        "Windows": {
            "Ctrl + L": {
                "Description": "Forward",
                "Category": "Email Management"
            },
            "Ctrl + R": {
                "Description": "Reply",
                "Category": "Email Management"
            },
            "Ctrl + K": {
                "Description": "Search messages",
                "Category": "Search"
            },
            "J": {
                "Description": "Mark as junk",
                "Category": "Message Management"
            },
            "Ctrl + N": {
                "Description": "New email",
                "Category": "Email Management"
            }
        }
    },
    "Notepad++": {
        "Windows": {
            "Ctrl + D": {
                "Description": "Duplicate current line",
                "Category": "Editing"
            },
            "F11": {
                "Description": "Toggle full screen",
                "Category": "View"
            },
            "Ctrl + Shift + W": {
                "Description": "Select word",
                "Category": "Selection"
            },
            "Ctrl + Shift + Down Arrow": {
                "Description": "Move line down",
                "Category": "Editing"
            },
            "Ctrl + F": {
                "Description": "Open find dialog",
                "Category": "Search"
            },
            "Ctrl + Shift + Up Arrow": {
                "Description": "Move line up",
                "Category": "Editing"
            },
            "Ctrl + G": {
                "Description": "Go to line",
                "Category": "Navigation"
            }
        }
    },
    "Notion": {
        "Windows": {
            "Ctrl + Shift + Arrow Up": {
                "Description": "Move block up",
                "Category": "Editing"
            },
            "Ctrl + Shift + Arrow Down": {
                "Description": "Move block down",
                "Category": "Editing"
            },
            "Ctrl + \\": {
                "Description": "Toggle sidebar",
                "Category": "Navigation"
            },
            "Ctrl + Shift + L": {
                "Description": "Switch to dark mode",
                "Category": "View"
            },
            "Ctrl + N": {
                "Description": "Create a new page",
                "Category": "File Management"
            },
            "Ctrl + Alt + T": {
                "Description": "Insert toggle list",
                "Category": "Inserting"
            },
            "Ctrl + D": {
                "Description": "Duplicate the current page",
                "Category": "Editing"
            },
            "Enter": {
                "Description": "Insert a new block",
                "Category": "Editing"
            }
        },
        "MacOS": {
            "Cmd + D": {
                "Description": "Duplicate the current page",
                "Category": "Editing"
            },
            "Cmd + \\": {
                "Description": "Toggle sidebar",
                "Category": "Navigation"
            },
            "Cmd + Shift + L": {
                "Description": "Switch to dark mode",
                "Category": "View"
            }
        }
    },
    "OBS Studio": {
        "Windows": {
            "Ctrl + S": {
                "Description": "Start/stop streaming",
                "Category": "Streaming"
            },
            "Ctrl + Number Keys": {
                "Description": "Switch scenes",
                "Category": "Scenes"
            },
            "Ctrl + R": {
                "Description": "Start/stop recording",
                "Category": "Recording"
            },
            "Ctrl + H": {
                "Description": "Toggle sources visibility",
                "Category": "View"
            },
            "Ctrl + M": {
                "Description": "Mute/unmute mic",
                "Category": "Audio"
            }
        }
    },
    "Obsidian": {
        "Windows": {
            "Ctrl + E": {
                "Description": "Toggle preview/edit mode",
                "Category": "View"
            },
            "Ctrl + O": {
                "Description": "Open quick switcher",
                "Category": "Navigation"
            },
            "Ctrl + P": {
                "Description": "Open command palette",
                "Category": "Tools"
            },
            "Ctrl + K": {
                "Description": "Insert link",
                "Category": "Inserting"
            },
            "Ctrl + B": {
                "Description": "Bold text",
                "Category": "Formatting"
            }
        }
    },
    "OneNote": {
        "Windows": {
            "Ctrl + N": {
                "Description": "Create new page",
                "Category": "File Management"
            },
            "Ctrl + Shift + T": {
                "Description": "Insert table",
                "Category": "Editing"
            },
            "Ctrl + Shift + H": {
                "Description": "Highlight text",
                "Category": "Formatting"
            },
            "Ctrl + G": {
                "Description": "Toggle notebook pane",
                "Category": "Navigation"
            }
        }
    },
    "Outlook": {
        "Windows": {
            "Ctrl + F": {
                "Description": "Forward email",
                "Category": "Email Management"
            },
            "Ctrl + R": {
                "Description": "Reply",
                "Category": "Email Management"
            },
            "Ctrl + Shift + M": {
                "Description": "New email",
                "Category": "Email Management"
            },
            "Ctrl + U": {
                "Description": "Mark as read/unread",
                "Category": "Message Management"
            },
            "Ctrl + 2": {
                "Description": "Open calendar",
                "Category": "Navigation"
            }
        }
    },
    "PyCharm": {
        "Windows": {
            "Shift + F6": {
                "Description": "Rename variable",
                "Category": "Editing"
            },
            "Ctrl + Alt + L": {
                "Description": "Format code",
                "Category": "Formatting"
            },
            "Ctrl + E": {
                "Description": "Open recent files",
                "Category": "Navigation"
            }
        },
        "MacOS": {
            "Cmd + E": {
                "Description": "Open recent files",
                "Category": "Navigation"
            },
            "Shift + Cmd + R": {
                "Description": "Rename variable",
                "Category": "Editing"
            },
            "Cmd + Alt + L": {
                "Description": "Format code",
                "Category": "Formatting"
            }
        }
    },
    "QuickBooks": {
        "Windows": {
            "Ctrl + A": {
                "Description": "Open chart of accounts",
                "Category": "Data Management"
            },
            "Ctrl + I": {
                "Description": "Create new invoice",
                "Category": "Invoicing"
            },
            "Ctrl + J": {
                "Description": "Go to customer list",
                "Category": "Navigation"
            },
            "Ctrl + R": {
                "Description": "Go to report center",
                "Category": "Reports"
            },
            "Ctrl + T": {
                "Description": "Create new transaction",
                "Category": "Transactions"
            }
        }
    },
    "Quip": {
        "Windows": {
            "Ctrl + K": {
                "Description": "Insert link",
                "Category": "Inserting"
            },
            "Ctrl + B": {
                "Description": "Bold text",
                "Category": "Formatting"
            },
            "Ctrl + I": {
                "Description": "Italicize text",
                "Category": "Formatting"
            },
            "Ctrl + Shift + X": {
                "Description": "Strikethrough text",
                "Category": "Formatting"
            },
            "Ctrl + U": {
                "Description": "Underline text",
                "Category": "Formatting"
            }
        }
    },
    "Salesforce": {
        "Windows": {
            "Alt + G": {
                "Description": "Open global search",
                "Category": "Search"
            },
            "Ctrl + E": {
                "Description": "Edit record",
                "Category": "Data Management"
            },
            "Alt + N": {
                "Description": "New record",
                "Category": "Data Management"
            },
            "Ctrl + D": {
                "Description": "Delete record",
                "Category": "Data Management"
            },
            "Ctrl + S": {
                "Description": "Save record",
                "Category": "Data Management"
            }
        }
    },
    "Sketch": {
        "MacOS": {
            "O": {
                "Description": "Insert oval",
                "Category": "Inserting"
            },
            "Cmd + R": {
                "Description": "Toggle rulers",
                "Category": "View"
            },
            "R": {
                "Description": "Insert rectangle",
                "Category": "Inserting"
            },
            "Cmd + G": {
                "Description": "Group layers",
                "Category": "Layers"
            },
            "Cmd + Shift + G": {
                "Description": "Ungroup layers",
                "Category": "Layers"
            }
        }
    },
    "Slack": {
        "Windows": {
            "Ctrl + Shift + T": {
                "Description": "Open threads view",
                "Category": "Communication"
            },
            "Up Arrow": {
                "Description": "Edit last message",
                "Category": "Editing"
            },
            "Ctrl + F": {
                "Description": "Search conversations",
                "Category": "Search"
            },
            "Ctrl + Shift + \\": {
                "Description": "Add reaction",
                "Category": "Messaging"
            },
            "Ctrl + Shift + Y": {
                "Description": "Set status",
                "Category": "User Settings"
            },
            "Ctrl + Shift + K": {
                "Description": "Open direct messages",
                "Category": "Navigation"
            },
            "Ctrl + Shift + Esc": {
                "Description": "Mark all messages as read",
                "Category": "Message Management"
            },
            "Ctrl + Shift + S": {
                "Description": "Toggle starred items",
                "Category": "Navigation"
            },
            "Esc": {
                "Description": "Mark channel as read",
                "Category": "Message Management"
            },
            "Alt + Shift + Up Arrow": {
                "Description": "Jump to next unread channel",
                "Category": "Navigation"
            },
            "Ctrl + Tab": {
                "Description": "Switch to next workspace",
                "Category": "Navigation"
            }
        },
        "MacOS": {
            "Cmd + Shift + Y": {
                "Description": "Set status",
                "Category": "User Settings"
            },
            "Cmd + Shift + Esc": {
                "Description": "Mark all messages as read",
                "Category": "Message Management"
            },
            "Cmd + F": {
                "Description": "Search conversations",
                "Category": "Search"
            },
            "Cmd + Shift + K": {
                "Description": "Open direct messages",
                "Category": "Navigation"
            },
            "Cmd + Tab": {
                "Description": "Switch to next workspace",
                "Category": "Navigation"
            }
        }
    },
    "Spotify": {
        "Windows": {
            "Ctrl + Up Arrow": {
                "Description": "Increase volume",
                "Category": "Volume"
            },
            "Space": {
                "Description": "Play/Pause",
                "Category": "Playback"
            },
            "Ctrl + Right Arrow": {
                "Description": "Next track",
                "Category": "Playback"
            },
            "Ctrl + Left Arrow": {
                "Description": "Previous track",
                "Category": "Playback"
            },
            "Ctrl + Down Arrow": {
                "Description": "Decrease volume",
                "Category": "Volume"
            }
        }
    },
    "Sublime Text": {
        "Windows": {
            "Ctrl + Shift + L": {
                "Description": "Select all occurrences",
                "Category": "Selection"
            },
            "Ctrl + /": {
                "Description": "Comment line",
                "Category": "Editing"
            },
            "Ctrl + Shift + P": {
                "Description": "Open command palette",
                "Category": "Tools"
            },
            "Ctrl + Shift + D": {
                "Description": "Duplicate line",
                "Category": "Editing"
            },
            "Ctrl + G": {
                "Description": "Go to line",
                "Category": "Navigation"
            }
        }
    },
    "Tableau": {
        "Windows": {
            "Ctrl + Shift + Z": {
                "Description": "Sort descending",
                "Category": "Sorting"
            },
            "Ctrl + Shift + H": {
                "Description": "Hide field",
                "Category": "Data Management"
            },
            "Ctrl + Shift + A": {
                "Description": "Sort ascending",
                "Category": "Sorting"
            },
            "Ctrl + D": {
                "Description": "Duplicate worksheet",
                "Category": "File Management"
            },
            "Ctrl + M": {
                "Description": "New worksheet",
                "Category": "File Management"
            }
        }
    },
    "Thunderbird": {
        "Windows": {
            "J": {
                "Description": "Mark as junk",
                "Category": "Message Management"
            },
            "Ctrl + K": {
                "Description": "Search messages",
                "Category": "Search"
            },
            "Ctrl + R": {
                "Description": "Reply",
                "Category": "Email Management"
            },
            "Ctrl + N": {
                "Description": "New email",
                "Category": "Email Management"
            },
            "Ctrl + L": {
                "Description": "Forward",
                "Category": "Email Management"
            }
        }
    },
    "Toggl": {
        "Windows": {
            "Ctrl + Shift + T": {
                "Description": "Stop timer",
                "Category": "Time Tracking"
            },
            "Ctrl + T": {
                "Description": "Start timer",
                "Category": "Time Tracking"
            },
            "Ctrl + R": {
                "Description": "Go to reports",
                "Category": "Navigation"
            },
            "Ctrl + F": {
                "Description": "Search entries",
                "Category": "Search"
            },
            "Ctrl + P": {
                "Description": "Open project list",
                "Category": "Project Management"
            }
        }
    },
    "Trello": {
        "Windows": {
            "Ctrl + Alt + C": {
                "Description": "Add card",
                "Category": "Tasks"
            },
            "F": {
                "Description": "Search cards",
                "Category": "Search"
            },
            "Ctrl + Shift + C": {
                "Description": "Add checklist",
                "Category": "Tasks"
            },
            "C": {
                "Description": "Archive card",
                "Category": "Tasks"
            },
            "B": {
                "Description": "Open board menu",
                "Category": "Navigation"
            }
        }
    },
    "Unity": {
        "Windows": {
            "Ctrl + P": {
                "Description": "Play game",
                "Category": "Playback"
            },
            "W": {
                "Description": "Move object",
                "Category": "Transform"
            },
            "Ctrl + Tab": {
                "Description": "Toggle scene/game view",
                "Category": "View"
            },
            "E": {
                "Description": "Rotate object",
                "Category": "Transform"
            },
            "Ctrl + D": {
                "Description": "Duplicate object",
                "Category": "Editing"
            }
        }
    },
    "VLC Media Player": {
        "Windows": {
            "Space": {
                "Description": "Play/Pause",
                "Category": "Playback"
            },
            "S": {
                "Description": "Stop playback",
                "Category": "Playback"
            },
            "Ctrl + Up Arrow": {
                "Description": "Increase volume",
                "Category": "Audio"
            }
        },
        "MacOS": {
            "Cmd + Up Arrow": {
                "Description": "Increase volume",
                "Category": "Audio"
            },
            "Cmd + .": {
                "Description": "Stop playback",
                "Category": "Playback"
            }
        }
    },
    "VS Code": {
        "Windows": {
            "F2": {
                "Description": "Rename symbol",
                "Category": "Editing"
            },
            "Ctrl + `": {
                "Description": "Toggle terminal",
                "Category": "Tools"
            },
            "F12": {
                "Description": "Go to definition",
                "Category": "Navigation"
            },
            "Ctrl + Shift + F": {
                "Description": "Find in files",
                "Category": "Search"
            },
            "Ctrl + Shift + L": {
                "Description": "Select all occurrences of word",
                "Category": "Selection"
            }
        }
    },
    "Visual Studio": {
        "Windows": {
            "Ctrl + Alt + L": {
                "Description": "Open solution explorer",
                "Category": "Navigation"
            },
            "F11": {
                "Description": "Step into",
                "Category": "Debugging"
            },
            "F10": {
                "Description": "Step over",
                "Category": "Debugging"
            },
            "F12": {
                "Description": "Go to definition",
                "Category": "Navigation"
            },
            "Ctrl + Shift + B": {
                "Description": "Build solution",
                "Category": "Build"
            },
            "F5": {
                "Description": "Start debugging",
                "Category": "Run"
            },
            "Ctrl + K, Ctrl + C": {
                "Description": "Toggle comment",
                "Category": "Editing"
            },
            "Ctrl + .": {
                "Description": "Quick actions",
                "Category": "Tools"
            },
            "Ctrl + F": {
                "Description": "Find",
                "Category": "Search"
            }
        }
    },
    "Visual Studio Code": {
        "MacOS": {
            "Shift + Cmd + F": {
                "Description": "Format document",
                "Category": "Formatting"
            },
            "Cmd + N": {
                "Description": "Open new file",
                "Category": "File Management"
            },
            "Cmd + Shift + P": {
                "Description": "Open command palette",
                "Category": "Tools"
            },
            "Cmd + `": {
                "Description": "Toggle terminal",
                "Category": "Tools"
            },
            "Cmd + S": {
                "Description": "Save file",
                "Category": "File Management"
            }
        },
        "Windows": {
            "Ctrl + N": {
                "Description": "Open new file",
                "Category": "File Management"
            },
            "Shift + F12": {
                "Description": "Find all references",
                "Category": "Search"
            },
            "Ctrl + /": {
                "Description": "Toggle comment line",
                "Category": "Editing"
            },
            "Ctrl + G": {
                "Description": "Go to line",
                "Category": "Navigation"
            },
            "Ctrl + Shift + P": {
                "Description": "Open command palette",
                "Category": "Tools"
            },
            "Ctrl + `": {
                "Description": "Toggle terminal",
                "Category": "Tools"
            },
            "Ctrl + Shift + X": {
                "Description": "Show extensions",
                "Category": "View"
            },
            "Shift + Alt + F": {
                "Description": "Format document",
                "Category": "Formatting"
            },
            "Ctrl + S": {
                "Description": "Save file",
                "Category": "File Management"
            }
        }
    },
    "Xcode": {
        "MacOS": {
            "Cmd + \\": {
                "Description": "Toggle breakpoints",
                "Category": "Debugging"
            },
            "Cmd + R": {
                "Description": "Build and run project",
                "Category": "Run"
            },
            "Cmd + L": {
                "Description": "Go to line",
                "Category": "Navigation"
            },
            "Cmd + 1": {
                "Description": "Open project navigator",
                "Category": "Navigation"
            },
            "Cmd + Shift + 0": {
                "Description": "Show documentation",
                "Category": "Help"
            }
        }
    },
    "Zendesk": {
        "Windows": {
            "A": {
                "Description": "Assign ticket",
                "Category": "Ticket Management"
            },
            "Ctrl + Shift + C": {
                "Description": "Close ticket",
                "Category": "Ticket Management"
            },
            "R": {
                "Description": "Reply to ticket",
                "Category": "Ticket Management"
            },
            "N": {
                "Description": "Create a new ticket",
                "Category": "Ticket Management"
            },
            "M": {
                "Description": "Merge ticket",
                "Category": "Ticket Management"
            }
        }
    },
    "Zoom": {
        "Windows": {
            "Alt + V": {
                "Description": "Start/stop video",
                "Category": "Video"
            },
            "Alt + A": {
                "Description": "Mute/unmute audio",
                "Category": "Audio"
            },
            "Alt + N": {
                "Description": "Switch camera",
                "Category": "Video"
            },
            "Alt + H": {
                "Description": "Toggle chat panel",
                "Category": "Communication"
            },
            "Alt + U": {
                "Description": "Toggle participants panel",
                "Category": "Communication"
            },
            "Alt + Q": {
                "Description": "End meeting",
                "Category": "Meeting Management"
            },
            "Alt + S": {
                "Description": "Share screen",
                "Category": "Screen Sharing"
            }
        }
    },
    "iTerm2": {
        "MacOS": {
            "Cmd + K": {
                "Description": "Clear buffer",
                "Category": "Buffer Management"
            },
            "Cmd + T": {
                "Description": "Create new tab",
                "Category": "Tab Management"
            },
            "Cmd + Enter": {
                "Description": "Toggle full screen",
                "Category": "View"
            },
            "Cmd + Shift + D": {
                "Description": "Split pane horizontally",
                "Category": "Pane Management"
            },
            "Cmd + W": {
                "Description": "Close current tab",
                "Category": "Tab Management"
            }
        }
    }
}